<?xml version="1.0" encoding="UTF-8"?>
<jcr:root xmlns:jcr="http://www.jcp.org/jcr/1.0" xmlns:nt="http://www.jcp.org/jcr/nt/1.0" xmlns:mix="http://www.jcp.org/jcr/mix/1.0" xmlns:cq="http://www.day.com/jcr/cq/1.0" xmlns:sling="http://sling.apache.org/jcr/sling/1.0"
    jcr:primaryType="cq:Page">
    <jcr:content
        cq:lastModified="{Date}2024-02-08T16:27:46.077Z"
        cq:lastModifiedBy="reference-adjustment-service"
        cq:template="/conf/menarini-berlinchemie/settings/wcm/templates/menarini---details-news"
        jcr:isCheckedOut="{Boolean}true"
        jcr:mixinTypes="[mix:versionable]"
        jcr:primaryType="cq:PageContent"
        jcr:title="Lost childhood: a 'tight-knit' network to combat abuse and distress"
        jcr:uuid="08d11c4b-c423-4333-9e5d-0d98cccac32c"
        sling:resourceType="menarinimaster/components/page"
        dnnNewsIdentifier="8a1c191b-1720-40aa-88de-c68d8076ed34-2788">
        <root
            jcr:primaryType="nt:unstructured"
            sling:resourceType="menarinimaster/components/container"
            layout="responsiveGrid">
            <container
                jcr:primaryType="nt:unstructured"
                sling:resourceType="menarinimaster/components/container"
                layout="responsiveGrid">
                <internalheader
                    jcr:primaryType="nt:unstructured"
                    jcr:title="News &amp; Medien"
                    sling:resourceType="menarinimaster/components/internalheader"
                    altValueFromDAM="{Boolean}false"
                    imageFromPageImage="{Boolean}false"
                    titleFromPage="{Boolean}false"/>
                <section
                    jcr:lastModified="{Date}2023-05-23T15:09:53.441Z"
                    jcr:lastModifiedBy="a.messori@adiacent.com"
                    jcr:primaryType="nt:unstructured"
                    sling:resourceType="menarinimaster/components/section">
                    <wrapper
                        jcr:lastModified="{Date}2023-05-23T15:11:01.995Z"
                        jcr:lastModifiedBy="a.messori@adiacent.com"
                        jcr:primaryType="nt:unstructured"
                        sling:resourceType="menarinimaster/components/wrapper">
                        <breadcrumb
                            jcr:primaryType="nt:unstructured"
                            sling:resourceType="menarinimaster/components/breadcrumb"/>
                    </wrapper>
                </section>
                <container
                    jcr:primaryType="nt:unstructured"
                    sling:resourceType="menarinimaster/components/container"
                    layout="responsiveGrid">
                    <internalmenu
                        jcr:primaryType="nt:unstructured"
                        sling:resourceType="menarinimaster/components/internalmenu"
                        navigationRoot="/content/menarini-berlinchemie/de/menarini-group-news"
                        structureStart="{Long}0">
                        <cq:responsive jcr:primaryType="nt:unstructured">
                            <default
                                jcr:primaryType="nt:unstructured"
                                offset="0"
                                width="3"/>
                            <tablet
                                jcr:primaryType="nt:unstructured"
                                offset="0"
                                width="4"/>
                            <phone
                                jcr:primaryType="nt:unstructured"
                                offset="0"
                                width="12"/>
                        </cq:responsive>
                    </internalmenu>
                    <container
                        cq:styleIds="[1684742346871]"
                        jcr:primaryType="nt:unstructured"
                        sling:resourceType="menarinimaster/components/container"
                        layout="responsiveGrid">
                        <news_data
                            jcr:primaryType="nt:unstructured"
                            sling:resourceType="menarinimaster/components/news_data"
                            newsDate="{Date}2022-11-29T18:16:00.000Z">
                            <cq:responsive jcr:primaryType="nt:unstructured">
                                <default
                                    jcr:primaryType="nt:unstructured"
                                    offset="0"
                                    width="9"/>
                            </cq:responsive>
                        </news_data>
                        <title
                            cq:styleIds="[1653552493699]"
                            jcr:lastModified="{Date}2023-06-07T15:16:13.835Z"
                            jcr:lastModifiedBy="d.mariotti@adiacent.com"
                            jcr:primaryType="nt:unstructured"
                            sling:resourceType="menarinimaster/components/title"
                            linkTarget="_self"
                            type="h2"/>
                        <image
                            jcr:lastModified="{Long}1707398330048"
                            jcr:lastModifiedBy="Importer"
                            jcr:primaryType="nt:unstructured"
                            sling:resourceType="menarinimaster/components/image"
                            displayPopupTitle="true"
                            fileReference="/content/dam/menarini-berlinchemie/assets/news/SFZ_0328.JPG"
                            imageFromPageImage="{Boolean}false"
                            isDecorative="true"
                            linkTarget="_self"
                            titleValueFromDAM="false">
                            <cq:responsive jcr:primaryType="nt:unstructured">
                                <default
                                    jcr:primaryType="nt:unstructured"
                                    offset="2"
                                    width="4"/>
                                <phone
                                    jcr:primaryType="nt:unstructured"
                                    offset="1"
                                    width="10"/>
                            </cq:responsive>
                        </image>
                        <spacer
                            jcr:lastModified="{Date}2023-06-07T15:17:27.212Z"
                            jcr:lastModifiedBy="d.mariotti@adiacent.com"
                            jcr:primaryType="nt:unstructured"
                            sling:resourceType="menarinimaster/components/spacer"
                            spacer="40"/>
                        <text
                            jcr:lastModified="{Long}1707398330052"
                            jcr:lastModifiedBy="Importer"
                            jcr:primaryType="nt:unstructured"
                            sling:resourceType="menarinimaster/components/text"
                            text="&lt;p align=&quot;center&quot; style=&quot;text-align:center; text-indent:35.4pt; margin-bottom:11px&quot;>&lt;b>&lt;i>On Radar&lt;/i>&lt;/b>&lt;b> takes off, the first meeting of the Think Tank of Fondazione Internazionale Menarini&lt;/b>&lt;/p>&#xa;&#xa;&lt;p style=&quot;text-align: center;&quot;>&lt;img loading=&quot;lazy&quot; src=&quot;/Portals/31/EasyDNNNews/2720/images/logo-on-radar-800-450-p-L-97.jpg&quot; style=&quot;max-width:450px;&quot; />&lt;/p>&#xa;&#xa;&lt;p>Rome, December 7th, 2022 &amp;ndash; Setting real changes in motion through dialogue among experts in order to tackle the unresolved issues of juvenile distress. This was the topic addressed during the first meeting of the &lt;b>&amp;#39;On Radar&lt;/b>&amp;#39; Think Tank of &lt;b>Fondazione Internazionale Menarini&lt;/b> held in Rome on November 29th.&lt;/p>&#xa;&#xa;&lt;p>&lt;i>&amp;ldquo;We believe that a company has the obligation to be part of the social fabric and to encourage dialogue even on the most neglected topics&lt;/i>&amp;rdquo; stated &lt;b>Lucia Aleotti&lt;/b>, shareholder and board member of &lt;b>Menarini&lt;/b>&lt;b> Group.&lt;/b>&lt;/p>&#xa;&#xa;&lt;p>&lt;b>On Radar&lt;/b> was born with the aim of observing society, identifying problems and committing to improve the environment in which we live. For its first event, 28 experts were involved, including paediatricians, psychologists, teachers, magistrates and officers of the Italian police force: all brought together to find concrete solutions to the phenomenon of &lt;b>abuse and violence against children and adolescents&lt;/b>, which for years now has taken on the proportions of a social scourge all over the world.&lt;/p>&#xa;&#xa;&lt;p>The working tables addressed the problem of child abuse in its various forms of physical and psychological ill-treatment, social isolation and poverty, with special focus on the suburban areas of cities.&lt;/p>&#xa;&#xa;&lt;p style=&quot;text-align: center;&quot;>&lt;img alt=&quot;&quot; loading=&quot;lazy&quot; src=&quot;/Portals/31/SFZ_0328.JPG&quot; style=&quot;max-width:550px;&quot; title=&quot;&quot; />&lt;/p>&#xa;&#xa;&lt;p>One the proposals that emerged is the &lt;b>creation of a permanent Observatory on abuse&lt;/b> care of the Judicial organs with periodic update meetings and the promotion of a &lt;b>network connecting&lt;/b> &lt;b>public prosecutors&amp;#39; offices and operators in the sector&lt;/b>, to foster dialogue and ensure that individual situations are properly dealt with. But that&amp;#39;s not all: &lt;b>involving paediatricians &lt;/b>was one of the topics discussed, in order to introduce potential indicators of distress in the drafting of the healthcare report, and the possible role of training courses for new mothers on the risk of disclosing photos of their children on social media, as they might become subject of child pornography.&lt;/p>&#xa;&#xa;&lt;p>In Italy there are about 9 million minors and of these &lt;b>9% suffers from abuse&lt;/b>, 85% of which is psychological, 10% physical and 3% sexual. Alarming data aggravated by the outbreak of the pandemic.&lt;/p>&#xa;&#xa;&lt;p style=&quot;text-align:justify; margin-bottom:11px&quot;>&lt;i>&amp;quot;Our ambitious intent,&amp;quot; &lt;/i>declared &lt;b>Massimo Scaccabarozzi&lt;/b>, president of On Radar&lt;i> &amp;quot;is to contribute to achieving a global condition of children&amp;#39;s health, in line with some of the goals of the UN&amp;rsquo;s 2030 Agenda, including, in particular, overcoming poverty and access to education&amp;rdquo;.&lt;/i>&lt;/p>"
                            textIsRich="true"/>
                        <cq:responsive jcr:primaryType="nt:unstructured">
                            <default
                                jcr:primaryType="nt:unstructured"
                                offset="0"
                                width="8"/>
                            <tablet
                                jcr:primaryType="nt:unstructured"
                                offset="0"
                                width="8"/>
                            <phone
                                jcr:primaryType="nt:unstructured"
                                offset="0"
                                width="12"/>
                        </cq:responsive>
                    </container>
                </container>
            </container>
        </root>
        <cq:featuredimage
            jcr:primaryType="nt:unstructured"
            sling:resourceType="core/wcm/components/image/v3/image"
            altValueFromDAM="{Boolean}false"
            fileReference="/content/dam/menarini-berlinchemie/assets/news/SFZ_0328.JPG"/>
    </jcr:content>
</jcr:root>
