<?xml version="1.0" encoding="UTF-8"?>
<jcr:root xmlns:jcr="http://www.jcp.org/jcr/1.0" xmlns:nt="http://www.jcp.org/jcr/nt/1.0" xmlns:sling="http://sling.apache.org/jcr/sling/1.0"
    jcr:primaryType="sling:OrderedFolder">
    <jcr:content
        jcr:primaryType="nt:unstructured"
        jcr:title="home"
        sourcing="false">
        <folderThumbnail/>
    </jcr:content>
    <cardhover_consumerhelthcare.jpg/>
    <cardhover_pharmaceutical.jpg/>
    <cardhover_diagnostics.jpg/>
    <cardhover_dermatology.jpg/>
    <cardhover_precisionmedicine.jpg/>
    <cardhover_innovation.jpg/>
    <cardhover_contact-us.jpg/>
    <banner/>
</jcr:root>
