<?xml version="1.0" encoding="UTF-8"?>
<jcr:root xmlns:jcr="http://www.jcp.org/jcr/1.0" xmlns:nt="http://www.jcp.org/jcr/nt/1.0" xmlns:mix="http://www.jcp.org/jcr/mix/1.0" xmlns:cq="http://www.day.com/jcr/cq/1.0" xmlns:sling="http://sling.apache.org/jcr/sling/1.0"
    jcr:primaryType="cq:Page">
    <jcr:content
        cq:lastModified="{Date}2023-04-19T14:03:39.391Z"
        cq:lastModifiedBy="m.papini@adiacent.com"
        cq:lastReplicated="{Date}2023-04-19T14:04:18.178Z"
        cq:lastReplicated_publish="{Date}2023-04-19T14:04:18.178Z"
        cq:lastReplicatedBy="m.papini@adiacent.com"
        cq:lastReplicatedBy_publish="m.papini@adiacent.com"
        cq:lastReplicationAction="Activate"
        cq:lastReplicationAction_publish="Activate"
        cq:template="/conf/menarini-stemline/settings/wcm/templates/menarini---details-page"
        jcr:isCheckedOut="{Boolean}true"
        jcr:mixinTypes="[mix:versionable]"
        jcr:primaryType="cq:PageContent"
        jcr:title="Mission"
        jcr:uuid="336f1c15-2eb2-4c4a-82af-3e87aa1d2501"
        sling:alias="mission"
        sling:resourceType="menarinimaster/components/page"
        pwaCachestrategy="staleWhileRevalidate"
        pwaDisplay="standalone"
        pwaOrientation="any">
        <root
            jcr:primaryType="nt:unstructured"
            sling:resourceType="menarinimaster/components/container"
            layout="responsiveGrid">
            <container
                jcr:primaryType="nt:unstructured"
                sling:resourceType="menarinimaster/components/container"
                layout="responsiveGrid">
                <internalheader
                    jcr:lastModified="{Date}2023-04-19T14:01:24.403Z"
                    jcr:lastModifiedBy="m.papini@adiacent.com"
                    jcr:primaryType="nt:unstructured"
                    jcr:title="About Us"
                    sling:resourceType="menarinimaster/components/internalheader"
                    disableLazyLoading="false"
                    fileReference="/content/dam/menarini-stemline/assets/header_about_us.jpg"
                    imageFromPageImage="false"
                    isDecorative="true"
                    textIsRich="true"
                    titleFromPage="false">
                    <cq:responsive jcr:primaryType="nt:unstructured">
                        <phone
                            jcr:primaryType="nt:unstructured"
                            offset="0"
                            width="12"/>
                    </cq:responsive>
                </internalheader>
                <breadcrumb
                    jcr:primaryType="nt:unstructured"
                    sling:resourceType="menarinimaster/components/breadcrumb"/>
                <container
                    jcr:primaryType="nt:unstructured"
                    sling:resourceType="menarinimaster/components/container"
                    layout="responsiveGrid">
                    <internalmenu
                        jcr:primaryType="nt:unstructured"
                        sling:resourceType="menarinimaster/components/internalmenu"
                        navigationRoot="/content/menarini-stemline/en/en/about-us"
                        structureStart="{Long}0">
                        <cq:responsive jcr:primaryType="nt:unstructured">
                            <default
                                jcr:primaryType="nt:unstructured"
                                offset="0"
                                width="3"/>
                            <tablet
                                jcr:primaryType="nt:unstructured"
                                offset="0"
                                width="4"/>
                            <phone
                                jcr:primaryType="nt:unstructured"
                                offset="0"
                                width="12"/>
                        </cq:responsive>
                    </internalmenu>
                    <container
                        cq:styleIds="[1655202404538]"
                        jcr:primaryType="nt:unstructured"
                        sling:resourceType="menarinimaster/components/container"
                        layout="responsiveGrid">
                        <title
                            cq:styleIds="[1653552493699]"
                            jcr:lastModified="{Date}2023-03-16T08:34:29.450Z"
                            jcr:lastModifiedBy="m.papini@adiacent.com"
                            jcr:primaryType="nt:unstructured"
                            jcr:title="Our Mission"
                            sling:resourceType="menarinimaster/components/title"
                            linkTarget="_self"
                            type="h2"/>
                        <title_copy_392490564_986227298
                            cq:styleIds="[1653552520338]"
                            jcr:lastModified="{Date}2023-03-28T08:20:59.143Z"
                            jcr:lastModifiedBy="m.papini@adiacent.com"
                            jcr:primaryType="nt:unstructured"
                            jcr:title="IMPROVEMENT"
                            sling:resourceType="menarinimaster/components/title"
                            linkTarget="_self"
                            type="h5">
                            <cq:responsive jcr:primaryType="nt:unstructured">
                                <default
                                    jcr:primaryType="nt:unstructured"
                                    offset="0"
                                    width="5"/>
                            </cq:responsive>
                        </title_copy_392490564_986227298>
                        <text_copy
                            jcr:lastModified="{Date}2023-03-01T13:57:56.988Z"
                            jcr:lastModifiedBy="m.papini@adiacent.com"
                            jcr:primaryType="nt:unstructured"
                            sling:resourceType="menarinimaster/components/text"
                            text="&lt;p>We’re dedicated to pushing the boundaries of cancer treatment and care, with a constant focus on improving our understanding of the disease and how to best serve patients.&lt;br>&#xd;&#xa;&lt;/p>&#xd;&#xa;"
                            textIsRich="true"/>
                        <title_copy_392490564
                            cq:styleIds="[1653552520338]"
                            jcr:lastModified="{Date}2023-03-28T08:21:10.752Z"
                            jcr:lastModifiedBy="m.papini@adiacent.com"
                            jcr:primaryType="nt:unstructured"
                            jcr:title="IMPACT"
                            sling:resourceType="menarinimaster/components/title"
                            linkTarget="_self"
                            type="h5">
                            <cq:responsive jcr:primaryType="nt:unstructured">
                                <default
                                    jcr:primaryType="nt:unstructured"
                                    offset="0"
                                    width="5"/>
                            </cq:responsive>
                        </title_copy_392490564>
                        <text_copy_288701424
                            jcr:lastModified="{Date}2023-03-01T13:58:48.083Z"
                            jcr:lastModifiedBy="m.papini@adiacent.com"
                            jcr:primaryType="nt:unstructured"
                            sling:resourceType="menarinimaster/components/text"
                            text="&lt;p>We’re dedicated to pushing the boundaries of cancer treatment and care, with a constant focus on improving our understanding of the disease and how to best serve patients.&lt;br>&#xd;&#xa;&lt;/p>&#xd;&#xa;"
                            textIsRich="true"/>
                        <title_copy_1989130660
                            cq:styleIds="[1653552520338]"
                            jcr:lastModified="{Date}2023-03-17T08:16:46.495Z"
                            jcr:lastModifiedBy="d.mariotti@adiacent.com"
                            jcr:primaryType="nt:unstructured"
                            jcr:title="TRUST"
                            sling:resourceType="menarinimaster/components/title"
                            linkTarget="_self"
                            type="h5">
                            <cq:responsive jcr:primaryType="nt:unstructured">
                                <default
                                    jcr:primaryType="nt:unstructured"
                                    offset="0"
                                    width="5"/>
                            </cq:responsive>
                        </title_copy_1989130660>
                        <text_copy_2081532065
                            jcr:lastModified="{Date}2023-03-01T13:59:08.669Z"
                            jcr:lastModifiedBy="m.papini@adiacent.com"
                            jcr:primaryType="nt:unstructured"
                            sling:resourceType="menarinimaster/components/text"
                            text="&lt;p>We are committed to achieving the highest standards of scientific and medical excellence in oncology and to be recognized as a trusted partner for patients, healthcare professionals, and researchers.&lt;br>&#xd;&#xa;&lt;/p>&#xd;&#xa;"
                            textIsRich="true"/>
                        <title_copy_1006943753
                            cq:styleIds="[1653552520338]"
                            jcr:lastModified="{Date}2023-03-15T13:32:01.715Z"
                            jcr:lastModifiedBy="m.papini@adiacent.com"
                            jcr:primaryType="nt:unstructured"
                            jcr:title="TRANSFORM"
                            sling:resourceType="menarinimaster/components/title"
                            linkTarget="_self"
                            type="h5">
                            <cq:responsive jcr:primaryType="nt:unstructured">
                                <default
                                    jcr:primaryType="nt:unstructured"
                                    offset="0"
                                    width="5"/>
                            </cq:responsive>
                        </title_copy_1006943753>
                        <text_copy_191736190
                            jcr:lastModified="{Date}2023-03-01T13:59:31.988Z"
                            jcr:lastModifiedBy="m.papini@adiacent.com"
                            jcr:primaryType="nt:unstructured"
                            sling:resourceType="menarinimaster/components/text"
                            text="&lt;p>We aspire to elevate the standards of oncology care through our heartfelt approach and to meaningfully transform the lives of those affected by cancer.&lt;br>&#xd;&#xa;&lt;/p>&#xd;&#xa;"
                            textIsRich="true"/>
                        <cq:responsive jcr:primaryType="nt:unstructured">
                            <default
                                jcr:primaryType="nt:unstructured"
                                offset="0"
                                width="8"/>
                            <tablet
                                jcr:primaryType="nt:unstructured"
                                offset="0"
                                width="8"/>
                            <phone
                                jcr:primaryType="nt:unstructured"
                                offset="0"
                                width="12"/>
                        </cq:responsive>
                    </container>
                    <cq:responsive jcr:primaryType="nt:unstructured">
                        <default
                            jcr:primaryType="nt:unstructured"
                            offset="0"
                            width="12"/>
                    </cq:responsive>
                    <container_539826219
                        jcr:lastModified="{Date}2023-04-14T07:31:20.095Z"
                        jcr:lastModifiedBy="m.papini@adiacent.com"
                        jcr:primaryType="nt:unstructured"
                        sling:resourceType="menarinimaster/components/container"
                        layout="responsiveGrid">
                        <container
                            jcr:lastModified="{Date}2023-04-14T07:33:20.929Z"
                            jcr:lastModifiedBy="m.papini@adiacent.com"
                            jcr:primaryType="nt:unstructured"
                            sling:resourceType="menarinimaster/components/container">
                            <spacer
                                jcr:lastModified="{Date}2023-03-28T08:21:33.957Z"
                                jcr:lastModifiedBy="m.papini@adiacent.com"
                                jcr:primaryType="nt:unstructured"
                                sling:resourceType="menarinimaster/components/spacer"
                                spacer="50"/>
                            <container
                                cq:styleIds="[1655202404538]"
                                jcr:lastModified="{Date}2023-04-14T07:33:42.792Z"
                                jcr:lastModifiedBy="m.papini@adiacent.com"
                                jcr:primaryType="nt:unstructured"
                                sling:resourceType="menarinimaster/components/container">
                                <container_copy
                                    jcr:lastModified="{Date}2023-04-14T07:33:58.717Z"
                                    jcr:lastModifiedBy="m.papini@adiacent.com"
                                    jcr:primaryType="nt:unstructured"
                                    sling:resourceType="menarinimaster/components/container"
                                    layout="responsiveGrid">
                                    <card_copy
                                        jcr:description="&lt;p>People are at the heart of the 4 key values we put into action each day.&lt;/p>&#xd;&#xa;"
                                        jcr:lastModified="{Date}2023-04-19T14:02:14.426Z"
                                        jcr:lastModifiedBy="m.papini@adiacent.com"
                                        jcr:primaryType="nt:unstructured"
                                        jcr:title="Our Values"
                                        sling:resourceType="menarinimaster/components/card"
                                        descriptionFromPage="false"
                                        disableLazyLoading="false"
                                        fileReference="/content/dam/menarini-stemline/assets/our_values.jpg"
                                        imageFromPageImage="false"
                                        isDecorative="true"
                                        linkTarget="_self"
                                        linkURL="/content/menarini-stemline/en/en/about-us/values"
                                        textIsRich="true"
                                        titleFromPage="false">
                                        <cq:responsive jcr:primaryType="nt:unstructured">
                                            <default
                                                jcr:primaryType="nt:unstructured"
                                                offset="0"
                                                width="6"/>
                                            <phone
                                                jcr:primaryType="nt:unstructured"
                                                offset="0"
                                                width="12"/>
                                            <tablet
                                                jcr:primaryType="nt:unstructured"
                                                offset="0"
                                                width="12"/>
                                        </cq:responsive>
                                        <actions jcr:primaryType="nt:unstructured">
                                            <item0
                                                jcr:primaryType="nt:unstructured"
                                                link="/content/menarini-stemline/en/en/about-us/values"
                                                linkTarget="_self"
                                                text="SEE YOUR VALUES"/>
                                        </actions>
                                    </card_copy>
                                    <card_copy_1356812176
                                        jcr:description="&lt;p>We are focused on the development of innovative, transformative therapies for oncology patients.&lt;/p>&#xd;&#xa;"
                                        jcr:lastModified="{Date}2023-04-19T14:03:10.567Z"
                                        jcr:lastModifiedBy="m.papini@adiacent.com"
                                        jcr:primaryType="nt:unstructured"
                                        jcr:title="Clinical Trials"
                                        sling:resourceType="menarinimaster/components/card"
                                        descriptionFromPage="false"
                                        disableLazyLoading="false"
                                        fileReference="/content/dam/menarini-stemline/assets/clinica_trials.jpg"
                                        imageFromPageImage="false"
                                        isDecorative="true"
                                        linkTarget="_self"
                                        linkURL="/content/menarini-stemline/en/en/science/research/clinical-trials"
                                        textIsRich="true"
                                        titleFromPage="false">
                                        <cq:responsive jcr:primaryType="nt:unstructured">
                                            <default
                                                jcr:primaryType="nt:unstructured"
                                                offset="0"
                                                width="6"/>
                                            <phone
                                                jcr:primaryType="nt:unstructured"
                                                offset="0"
                                                width="12"/>
                                            <tablet
                                                jcr:primaryType="nt:unstructured"
                                                offset="0"
                                                width="12"/>
                                        </cq:responsive>
                                        <actions jcr:primaryType="nt:unstructured">
                                            <item0
                                                jcr:primaryType="nt:unstructured"
                                                link="/content/menarini-stemline/en/en/science/research/clinical-trials"
                                                linkTarget="_self"
                                                text="EXPLORE OUR TRIALS"/>
                                        </actions>
                                    </card_copy_1356812176>
                                    <spacer_copy
                                        jcr:lastModified="{Date}2023-04-14T07:38:32.997Z"
                                        jcr:lastModifiedBy="m.papini@adiacent.com"
                                        jcr:primaryType="nt:unstructured"
                                        sling:resourceType="menarinimaster/components/spacer"
                                        spacer="50"/>
                                </container_copy>
                                <banner_copy_copy
                                    cq:styleIds="[1655107229265]"
                                    jcr:description="&lt;p>Our employees make all the difference—every day. Want to learn more about becoming part of our international family?&lt;/p>&#xd;&#xa;"
                                    jcr:lastModified="{Date}2023-04-19T14:03:39.376Z"
                                    jcr:lastModifiedBy="m.papini@adiacent.com"
                                    jcr:primaryType="nt:unstructured"
                                    jcr:title="OPEN POSITIONS"
                                    sling:resourceType="menarinimaster/components/banner"
                                    descriptionFromPage="false"
                                    disableLazyLoading="false"
                                    fileReference="/content/dam/menarini-stemline/assets/megabox_Open_Positions.jpg"
                                    imageFromPageImage="false"
                                    isDecorative="true"
                                    linkTarget="_blank"
                                    linkURL="https://www.menarini.com/en-us/careers/careers-in-oncology"
                                    textIsRich="true"
                                    titleFromPage="false">
                                    <cq:responsive jcr:primaryType="nt:unstructured">
                                        <phone
                                            jcr:primaryType="nt:unstructured"
                                            offset="0"
                                            width="11"/>
                                        <tablet
                                            jcr:primaryType="nt:unstructured"
                                            offset="0"
                                            width="11"/>
                                        <default
                                            jcr:primaryType="nt:unstructured"
                                            offset="0"
                                            width="11"/>
                                    </cq:responsive>
                                    <actions jcr:primaryType="nt:unstructured">
                                        <item0
                                            jcr:primaryType="nt:unstructured"
                                            link="https://www.menarini.com/en-us/careers/careers-in-oncology"
                                            linkTarget="_self"
                                            text="EXPLORE OUR CAREERS"/>
                                    </actions>
                                </banner_copy_copy>
                            </container>
                        </container>
                        <container_783626285
                            jcr:lastModified="{Date}2023-03-21T16:22:52.473Z"
                            jcr:lastModifiedBy="j.kaur@adiacent.com"
                            jcr:primaryType="nt:unstructured"
                            sling:resourceType="menarinimaster/components/container"/>
                    </container_539826219>
                </container>
            </container>
        </root>
        <cq:featuredimage
            jcr:lastModified="{Date}2023-03-01T10:34:06.399Z"
            jcr:lastModifiedBy="m.papini@adiacent.com"
            jcr:primaryType="nt:unstructured"
            sling:resourceType="core/wcm/components/image/v3/image"
            altValueFromDAM="false"/>
    </jcr:content>
</jcr:root>
