<?xml version="1.0" encoding="UTF-8"?>
<jcr:root xmlns:jcr="http://www.jcp.org/jcr/1.0" xmlns:nt="http://www.jcp.org/jcr/nt/1.0" xmlns:rep="internal" xmlns:cq="http://www.day.com/jcr/cq/1.0" xmlns:sling="http://sling.apache.org/jcr/sling/1.0"
    jcr:mixinTypes="[rep:AccessControllable]"
    jcr:primaryType="cq:Page">
    <rep:policy/>
    <fondazione jcr:primaryType="nt:unstructured">
        <components jcr:primaryType="nt:unstructured">
            <slideshow jcr:primaryType="nt:unstructured">
                <policy_1724932614537
                    cq:styleDefaultClasses="cmp-slideshow-primary-button"
                    jcr:lastModified="{Date}2024-08-29T14:57:47.340+03:00"
                    jcr:lastModifiedBy="admin"
                    jcr:primaryType="nt:unstructured"
                    jcr:title="Slideshow policy"
                    sling:resourceType="wcm/core/components/policy/policy">
                    <jcr:content jcr:primaryType="nt:unstructured"/>
                    <cq:styleGroups jcr:primaryType="nt:unstructured">
                        <item0
                            cq:styleGroupLabel="Color"
                            jcr:primaryType="nt:unstructured">
                            <cq:styles jcr:primaryType="nt:unstructured">
                                <item0
                                    cq:styleClasses="cmp-slideshow-primary-button"
                                    cq:styleId="1724932635352"
                                    cq:styleLabel="Primary"
                                    jcr:primaryType="nt:unstructured"/>
                                <item1
                                    cq:styleClasses="cmp-slideshow-secondary-button"
                                    cq:styleId="1724932650958"
                                    cq:styleLabel="Secondary"
                                    jcr:primaryType="nt:unstructured"/>
                            </cq:styles>
                        </item0>
                    </cq:styleGroups>
                </policy_1724932614537>
            </slideshow>
            <banner-app jcr:primaryType="nt:unstructured">
                <banner-app-container jcr:primaryType="nt:unstructured">
                    <policy_1725368925556
                        jcr:lastModified="{Date}2024-09-04T13:00:54.962+02:00"
                        jcr:lastModifiedBy="admin"
                        jcr:primaryType="nt:unstructured"
                        jcr:title="Banner apps container policy"
                        sling:resourceType="wcm/core/components/policy/policy"
                        backgroundImageEnabled="true"
                        components="/apps/fondazione/components/banner-app/banner-app-teaser"
                        layoutDisabled="false">
                        <jcr:content jcr:primaryType="nt:unstructured"/>
                    </policy_1725368925556>
                    <policy_69283547620834
                        jcr:lastModified="{Date}2024-09-05T17:50:02.839+03:00"
                        jcr:lastModifiedBy="admin"
                        jcr:primaryType="nt:unstructured"
                        jcr:title="Banner apps container"
                        sling:resourceType="wcm/core/components/policy/policy"
                        backgroundImageEnabled="true"
                        layoutDisabled="false">
                        <jcr:content jcr:primaryType="nt:unstructured"/>
                    </policy_69283547620834>
                    <policy_69377665109750
                        jcr:lastModified="{Date}2024-09-05T17:51:32.429+03:00"
                        jcr:lastModifiedBy="admin"
                        jcr:primaryType="nt:unstructured"
                        jcr:title="Banner apps policy"
                        sling:resourceType="wcm/core/components/policy/policy"
                        backgroundImageEnabled="true"
                        layoutDisabled="false">
                        <jcr:content jcr:primaryType="nt:unstructured"/>
                    </policy_69377665109750>
                </banner-app-container>
            </banner-app>
            <banner-mobile-app jcr:primaryType="nt:unstructured">
                <banner-mobile-app-container jcr:primaryType="nt:unstructured">
                    <policy_1726061095737
                        jcr:lastModified="{Date}2024-09-11T16:25:24.026+03:00"
                        jcr:lastModifiedBy="admin"
                        jcr:primaryType="nt:unstructured"
                        jcr:title="Banner Mobile App Container Policy"
                        sling:resourceType="wcm/core/components/policy/policy"
                        backgroundImageEnabled="true"
                        components="/apps/fondazione/components/banner-mobile-app/banner-mobile-app-teaser"
                        layoutDisabled="false">
                        <jcr:content jcr:primaryType="nt:unstructured"/>
                    </policy_1726061095737>
                </banner-mobile-app-container>
            </banner-mobile-app>
            <horizontal-teaser jcr:primaryType="nt:unstructured">
                <policy_1726149355415
                    cq:styleDefaultClasses="cmp-horizontal-teaser-left"
                    jcr:lastModified="{Date}2024-09-12T17:10:54.012+03:00"
                    jcr:lastModifiedBy="admin"
                    jcr:primaryType="nt:unstructured"
                    jcr:title="Horizontal Teaser"
                    sling:resourceType="wcm/core/components/policy/policy"
                    allowedHeadingElements="[h1,h2,h3,h4,h5,h6]"
                    pretitleHidden="true"
                    showTitleType="false"
                    titleType="h2">
                    <jcr:content jcr:primaryType="nt:unstructured"/>
                    <cq:styleGroups jcr:primaryType="nt:unstructured">
                        <item0
                            cq:styleGroupLabel="Custom"
                            jcr:primaryType="nt:unstructured">
                            <cq:styles jcr:primaryType="nt:unstructured">
                                <item0
                                    cq:styleClasses="cmp-horizontal-teaser-left"
                                    cq:styleId="1726149359810"
                                    cq:styleLabel="left"
                                    jcr:primaryType="nt:unstructured"/>
                                <item1
                                    cq:styleClasses="cmp-horizontal-teaser-right"
                                    cq:styleId="1726149422099"
                                    cq:styleLabel="right"
                                    jcr:primaryType="nt:unstructured"/>
                            </cq:styles>
                        </item0>
                    </cq:styleGroups>
                </policy_1726149355415>
            </horizontal-teaser>
            <card-grid jcr:primaryType="nt:unstructured">
                <card-grid-container jcr:primaryType="nt:unstructured">
                    <policy_1726213078559
                        jcr:lastModified="{Date}2024-09-13T17:38:37.209+03:00"
                        jcr:lastModifiedBy="admin"
                        jcr:primaryType="nt:unstructured"
                        jcr:title="Card Grid Item"
                        sling:resourceType="wcm/core/components/policy/policy"
                        components="/apps/fondazione/components/card-grid/card-grid-item"
                        layout="responsiveGrid"
                        layoutDisabled="true">
                        <jcr:content jcr:primaryType="nt:unstructured"/>
                    </policy_1726213078559>
                    <policy_6794108572209
                        jcr:lastModified="{Date}2024-09-16T12:57:26.232+03:00"
                        jcr:lastModifiedBy="admin"
                        jcr:primaryType="nt:unstructured"
                        jcr:title="Card Grid container"
                        sling:resourceType="wcm/core/components/policy/policy"
                        components="/apps/fondazione/components/card-grid/card-grid-item"
                        layoutDisabled="false">
                        <jcr:content jcr:primaryType="nt:unstructured"/>
                    </policy_6794108572209>
                </card-grid-container>
                <card-grid-item jcr:primaryType="nt:unstructured">
                    <policy_1726213170851
                        jcr:lastModified="{Date}2024-09-13T10:39:49.483+03:00"
                        jcr:lastModifiedBy="admin"
                        jcr:primaryType="nt:unstructured"
                        jcr:title="Card Grid Item"
                        sling:resourceType="wcm/core/components/policy/policy"
                        actionsDisabled="true"
                        allowedHeadingElements="[h1,h2,h3,h4,h5,h6]"
                        pretitleHidden="true"
                        showTitleType="true"
                        titleType="h2">
                        <jcr:content jcr:primaryType="nt:unstructured"/>
                    </policy_1726213170851>
                </card-grid-item>
            </card-grid>
            <form jcr:primaryType="nt:unstructured">
                <container jcr:primaryType="nt:unstructured">
                    <form-container
                        jcr:description="Allows the form components to be dropped into this core form container."
                        jcr:primaryType="nt:unstructured"
                        jcr:title="Content Form"
                        sling:resourceType="wcm/core/components/policy/policy"
                        components="[/apps/fondazione/components/form/button,/apps/fondazione/components/form/hidden,/apps/fondazione/components/form/options,/apps/fondazione/components/form/text]">
                        <jcr:content jcr:primaryType="nt:unstructured"/>
                    </form-container>
                </container>
            </form>
            <languagenavigation jcr:primaryType="nt:unstructured">
                <policy_xfm
                    jcr:primaryType="nt:unstructured"
                    jcr:title="Fondazione Language Navigation - Experience Fragment"
                    sling:resourceType="wcm/core/components/policy/policy"
                    navigationRoot="/content/fondazione"
                    structureDepth="1">
                    <jcr:content jcr:primaryType="nt:unstructured"/>
                </policy_xfm>
            </languagenavigation>
            <image jcr:primaryType="nt:unstructured">
                <policy_651483963895698
                    jcr:description="- Enable lazy loading for faster page loading.&#xd;&#xa;- Define allowed image widths for automatic loading of the image in the most optimal resolution, given the size at which each image is displayed on the page, and the visitor's pixel density.&#xd;&#xa;- Disallow direct asset upload, to force authors to first upload the images to Assets."
                    jcr:primaryType="nt:unstructured"
                    jcr:title="Content Image"
                    sling:resourceType="wcm/core/components/policy/policy"
                    allowedRenditionWidths="[320,480,600,800,1024,1200,1600]"
                    allowUpload="false"
                    altValueFromDAM="true"
                    disableLazyLoading="false"
                    displayPopupTitle="true"
                    enableAssetDelivery="true"
                    isDecorative="false"
                    jpegQuality="{Long}85"
                    titleValueFromDAM="true"
                    uuidDisabled="true">
                    <jcr:content jcr:primaryType="nt:unstructured"/>
                    <plugins jcr:primaryType="nt:unstructured">
                        <crop
                            jcr:primaryType="nt:unstructured"
                            features="*">
                            <aspectRatios jcr:primaryType="nt:unstructured">
                                <item0
                                    jcr:primaryType="nt:unstructured"
                                    name="Wide Landscape"
                                    ratio="0.6180"/>
                                <item1
                                    jcr:primaryType="nt:unstructured"
                                    name="Landscape"
                                    ratio="0.8284"/>
                                <item2
                                    jcr:primaryType="nt:unstructured"
                                    name="Square"
                                    ratio="1"/>
                                <item3
                                    jcr:primaryType="nt:unstructured"
                                    name="Portrait"
                                    ratio="1.6180"/>
                            </aspectRatios>
                        </crop>
                        <rotate
                            jcr:primaryType="nt:unstructured"
                            features="right"/>
                        <flip
                            jcr:primaryType="nt:unstructured"
                            features="-"/>
                    </plugins>
                </policy_651483963895698>
            </image>
            <text jcr:primaryType="nt:unstructured">
                <policy_641562756958017
                    jcr:primaryType="nt:unstructured"
                    jcr:title="Content Text"
                    sling:resourceType="wcm/core/components/policy/policy">
                    <jcr:content jcr:primaryType="nt:unstructured"/>
                    <rtePlugins jcr:primaryType="nt:unstructured">
                        <paraformat
                            jcr:primaryType="nt:unstructured"
                            features="*">
                            <formats
                                jcr:primaryType="nt:unstructured"
                                override="true">
                                <item0
                                    jcr:primaryType="nt:unstructured"
                                    description="Paragraph"
                                    tag="p"/>
                                <item1
                                    jcr:primaryType="nt:unstructured"
                                    description="Quote"
                                    tag="blockquote"/>
                                <item2
                                    jcr:primaryType="nt:unstructured"
                                    description="Preformatted"
                                    tag="pre"/>
                            </formats>
                        </paraformat>
                        <misctools
                            jcr:primaryType="nt:unstructured"
                            features="-">
                            <specialCharsConfig jcr:primaryType="nt:unstructured">
                                <chars
                                    jcr:primaryType="nt:unstructured"
                                    override="true">
                                    <item0
                                        jcr:primaryType="nt:unstructured"
                                        entity="&amp;copy;"
                                        name="copyright"/>
                                    <item1
                                        jcr:primaryType="nt:unstructured"
                                        entity="&amp;euro;"
                                        name="euro"/>
                                    <item2
                                        jcr:primaryType="nt:unstructured"
                                        entity="&amp;reg;"
                                        name="registered"/>
                                    <item3
                                        jcr:primaryType="nt:unstructured"
                                        entity="&amp;trade;"
                                        name="trademark"/>
                                </chars>
                            </specialCharsConfig>
                        </misctools>
                        <edit
                            jcr:primaryType="nt:unstructured"
                            features="-"/>
                        <findreplace
                            jcr:primaryType="nt:unstructured"
                            features="-"/>
                        <undo
                            jcr:primaryType="nt:unstructured"
                            features="-"/>
                        <spellcheck
                            jcr:primaryType="nt:unstructured"
                            features="-"/>
                        <image
                            jcr:primaryType="nt:unstructured"
                            features="-"/>
                        <table
                            jcr:primaryType="nt:unstructured"
                            features="-"/>
                        <lists
                            jcr:primaryType="nt:unstructured"
                            features="*"/>
                        <justify
                            jcr:primaryType="nt:unstructured"
                            features="-"/>
                        <format
                            jcr:primaryType="nt:unstructured"
                            features="bold,italic"/>
                        <links
                            jcr:primaryType="nt:unstructured"
                            features="modifylink,unlink"/>
                        <subsuperscript
                            jcr:primaryType="nt:unstructured"
                            features="-"/>
                    </rtePlugins>
                </policy_641562756958017>
            </text>
            <title jcr:primaryType="nt:unstructured">
                <policy_641475696923109
                    jcr:description="Allows only H1 and disallows links for the main page title."
                    jcr:primaryType="nt:unstructured"
                    jcr:title="Page Title"
                    sling:resourceType="wcm/core/components/policy/policy"
                    allowedTypes="h1"
                    linkDisabled="true"
                    type="h1">
                    <jcr:content jcr:primaryType="nt:unstructured"/>
                </policy_641475696923109>
                <policy_641528232375303
                    jcr:description="Allows all sizes, but not H1, which is reserved for the main page title."
                    jcr:lastModified="{Date}2024-09-13T16:28:09.840+02:00"
                    jcr:lastModifiedBy="admin"
                    jcr:primaryType="nt:unstructured"
                    jcr:title="Content Title"
                    sling:resourceType="wcm/core/components/policy/policy"
                    allowedTypes="[h2,h3,h4,h5,h6]"
                    linkDisabled="false"
                    type="h2">
                    <jcr:content jcr:primaryType="nt:unstructured"/>
                </policy_641528232375303>
            </title>
            <experiencefragment jcr:primaryType="nt:unstructured">
                <policy_header
                    cq:styleDefaultElement="header"
                    jcr:description="Sets a &lt;header> element on the page header experience fragment."
                    jcr:primaryType="nt:unstructured"
                    jcr:title="Page Header"
                    sling:resourceType="wcm/core/components/policy/policy">
                    <jcr:content jcr:primaryType="nt:unstructured"/>
                </policy_header>
                <policy_footer
                    cq:styleDefaultElement="footer"
                    jcr:description="Sets a &lt;footer> element on the page footer experience fragment."
                    jcr:primaryType="nt:unstructured"
                    jcr:title="Page Footer"
                    sling:resourceType="wcm/core/components/policy/policy">
                    <jcr:content jcr:primaryType="nt:unstructured"/>
                </policy_footer>
            </experiencefragment>
            <container jcr:primaryType="nt:unstructured">
                <policy_1574694950110
                    cq:styleDefaultClasses="container-fluid"
                    jcr:description="Allows the template components and defines the component mapping (this configures what components should be automatically created when authors drop assets from the content finder to the page editor)."
                    jcr:lastModified="{Date}2024-09-16T15:47:02.024+02:00"
                    jcr:lastModifiedBy="admin"
                    jcr:primaryType="nt:unstructured"
                    jcr:title="Page Root"
                    sling:resourceType="wcm/core/components/policy/policy"
                    components="[group:Fondazione - Content,/apps/fondazione/components/form/container,group:Fondazione - Structure]"
                    layoutDisabled="false">
                    <jcr:content jcr:primaryType="nt:unstructured"/>
                    <cq:authoring jcr:primaryType="nt:unstructured">
                        <assetToComponentMapping jcr:primaryType="nt:unstructured">
                            <mapping_1575024218483
                                jcr:primaryType="nt:unstructured"
                                assetGroup="media"
                                assetMimetype="image/*"
                                droptarget="image"
                                resourceType="fondazione/components/image"/>
                            <mapping_1575030843388
                                jcr:primaryType="nt:unstructured"
                                assetGroup="content"
                                assetMimetype="text/html"
                                droptarget="experiencefragment"
                                resourceType="fondazione/components/experiencefragment"/>
                            <mapping_1575030853128
                                jcr:primaryType="nt:unstructured"
                                assetGroup="media"
                                assetMimetype="[text/html,application/vnd.adobe.contentfragment]"
                                droptarget="contentfragment"
                                resourceType="fondazione/components/contentfragment"/>
                        </assetToComponentMapping>
                    </cq:authoring>
                </policy_1574694950110>
                <policy_1574695586800
                    cq:styleDefaultClasses="container-fluid"
                    jcr:description="Allows the page components and defines the component mapping (this configures what components should be automatically created when authors drop assets from the content finder to the page editor)."
                    jcr:lastModified="{Date}2024-09-13T15:47:48.765+02:00"
                    jcr:lastModifiedBy="admin"
                    jcr:primaryType="nt:unstructured"
                    jcr:title="Page Content"
                    sling:resourceType="wcm/core/components/policy/policy"
                    components="[group:Fondazione - Content,/apps/fondazione/components/form/container]"
                    layout="responsiveGrid"
                    layoutDisabled="false">
                    <jcr:content jcr:primaryType="nt:unstructured"/>
                    <cq:authoring jcr:primaryType="nt:unstructured">
                        <assetToComponentMapping jcr:primaryType="nt:unstructured">
                            <mapping_1575030255082
                                jcr:primaryType="nt:unstructured"
                                assetGroup="media"
                                assetMimetype="image/*"
                                droptarget="image"
                                resourceType="fondazione/components/image"/>
                            <mapping_1575030260142
                                jcr:primaryType="nt:unstructured"
                                assetGroup="content"
                                assetMimetype="text/html"
                                droptarget="experiencefragment"
                                resourceType="fondazione/components/experiencefragment"/>
                            <mapping_1575030269139
                                jcr:primaryType="nt:unstructured"
                                assetGroup="media"
                                assetMimetype="[text/html,application/vnd.adobe.contentfragment]"
                                droptarget="contentfragment"
                                resourceType="fondazione/components/contentfragment"/>
                        </assetToComponentMapping>
                    </cq:authoring>
                    <cq:styleGroups jcr:primaryType="nt:unstructured">
                        <item0 jcr:primaryType="nt:unstructured">
                            <cq:styles jcr:primaryType="nt:unstructured">
                                <item0
                                    cq:styleClasses="container-fluid"
                                    cq:styleId="1726235249991"
                                    cq:styleLabel="Full Width"
                                    jcr:primaryType="nt:unstructured"/>
                            </cq:styles>
                        </item0>
                    </cq:styleGroups>
                </policy_1574695586800>
                <policy_649128221558427
                    cq:styleDefaultElement="main"
                    jcr:description="Sets a &lt;main> element on the page content area."
                    jcr:primaryType="nt:unstructured"
                    jcr:title="Page Main"
                    sling:resourceType="wcm/core/components/policy/policy">
                    <jcr:content jcr:primaryType="nt:unstructured"/>
                </policy_649128221558427>
                <policy_1575040440977
                    jcr:description="Allows the template components and defines the component mapping (this configures what components should be automatically created when authors drop assets from the content finder to the page editor)."
                    jcr:lastModified="{Date}2024-09-11T11:14:35.850+03:00"
                    jcr:lastModifiedBy="admin"
                    jcr:primaryType="nt:unstructured"
                    jcr:title="XF Root"
                    sling:resourceType="wcm/core/components/policy/policy"
                    components="[group:Fondazione - Content,/apps/fondazione/components/form/container]"
                    layoutDisabled="false">
                    <jcr:content jcr:primaryType="nt:unstructured"/>
                    <cq:authoring jcr:primaryType="nt:unstructured">
                        <assetToComponentMapping jcr:primaryType="nt:unstructured">
                            <mapping_1575024218483
                                jcr:primaryType="nt:unstructured"
                                assetGroup="media"
                                assetMimetype="image/*"
                                droptarget="image"
                                resourceType="fondazione/components/image"/>
                            <mapping_1575030843388
                                jcr:primaryType="nt:unstructured"
                                assetGroup="content"
                                assetMimetype="text/html"
                                droptarget="experiencefragment"
                                resourceType="fondazione/components/experiencefragment"/>
                            <mapping_1575030853128
                                jcr:primaryType="nt:unstructured"
                                assetGroup="media"
                                assetMimetype="[text/html,application/vnd.adobe.contentfragment]"
                                droptarget="contentfragment"
                                resourceType="fondazione/components/contentfragment"/>
                        </assetToComponentMapping>
                    </cq:authoring>
                </policy_1575040440977>
                <policy_34977012579416
                    jcr:lastModified="{Date}2024-09-17T01:03:58.619+02:00"
                    jcr:lastModifiedBy="admin"
                    jcr:primaryType="nt:unstructured"
                    jcr:title="Container Default Layout"
                    sling:resourceType="wcm/core/components/policy/policy"
                    layout="responsiveGrid"
                    layoutDisabled="true">
                    <jcr:content jcr:primaryType="nt:unstructured"/>
                </policy_34977012579416>
            </container>
            <teaser jcr:primaryType="nt:unstructured">
                <policy_1575031387650
                    jcr:description="Sets the title size to H3."
                    jcr:lastModified="{Date}2024-09-03T14:32:54.356+03:00"
                    jcr:lastModifiedBy="admin"
                    jcr:primaryType="nt:unstructured"
                    jcr:title="Content Teaser"
                    sling:resourceType="wcm/core/components/policy/policy"
                    allowedHeadingElements="[h1,h2,h3,h4,h5,h6]"
                    pretitleHidden="true"
                    showTitleType="false"
                    titleType="h3">
                    <jcr:content jcr:primaryType="nt:unstructured"/>
                    <cq:styleGroups jcr:primaryType="nt:unstructured">
                        <item0
                            cq:styleGroupLabel="Custom Styles"
                            jcr:primaryType="nt:unstructured">
                            <cq:styles jcr:primaryType="nt:unstructured">
                                <item0
                                    cq:styleClasses="cmp-teaser--custom-left"
                                    cq:styleId="1725363004060"
                                    cq:styleLabel="left"
                                    jcr:primaryType="nt:unstructured"/>
                                <item1
                                    cq:styleClasses="cmp-teaser--custom-right"
                                    cq:styleId="1725363023170"
                                    cq:styleLabel="right"
                                    jcr:primaryType="nt:unstructured"/>
                            </cq:styles>
                        </item0>
                    </cq:styleGroups>
                </policy_1575031387650>
                <policy_69396254658917
                    jcr:lastModified="{Date}2024-09-05T17:52:15.975+03:00"
                    jcr:lastModifiedBy="admin"
                    jcr:primaryType="nt:unstructured"
                    jcr:title="Teaser policy"
                    sling:resourceType="wcm/core/components/policy/policy"
                    allowedHeadingElements="[h1,h2,h3,h4,h5,h6]"
                    showTitleType="false"
                    titleType="h2">
                    <jcr:content jcr:primaryType="nt:unstructured"/>
                    <cq:styleGroups jcr:primaryType="nt:unstructured">
                        <item0
                            cq:styleGroupLabel="Custom"
                            jcr:primaryType="nt:unstructured">
                            <cq:styles jcr:primaryType="nt:unstructured">
                                <item0
                                    cq:styleClasses="cmp-teaser--custom-left"
                                    cq:styleId="1725547917077"
                                    cq:styleLabel="left"
                                    jcr:primaryType="nt:unstructured"/>
                                <item1
                                    cq:styleClasses="cmp-teaser--custom-right"
                                    cq:styleId="1725547925164"
                                    cq:styleLabel="right"
                                    jcr:primaryType="nt:unstructured"/>
                            </cq:styles>
                        </item0>
                    </cq:styleGroups>
                </policy_69396254658917>
            </teaser>
            <download jcr:primaryType="nt:unstructured">
                <policy_1575032193319
                    jcr:description="Sets the title size to H3."
                    jcr:primaryType="nt:unstructured"
                    jcr:title="Content Download"
                    sling:resourceType="wcm/core/components/policy/policy"
                    allowUpload="false"
                    displayFilename="true"
                    displayFormat="true"
                    displaySize="true"
                    titleType="h3">
                    <jcr:content jcr:primaryType="nt:unstructured"/>
                </policy_1575032193319>
            </download>
            <page jcr:primaryType="nt:unstructured">
                <policy
                    jcr:description="Includes the required client libraries."
                    jcr:primaryType="nt:unstructured"
                    jcr:title="Generic Page"
                    sling:resourceType="wcm/core/components/policy/policy"
                    clientlibs="[fondazione.dependencies,fondazione.site]"
                    clientlibsJsHead="fondazione.dependencies">
                    <jcr:content jcr:primaryType="nt:unstructured"/>
                </policy>
            </page>
        </components>
    </fondazione>
    <wcm jcr:primaryType="nt:unstructured">
        <foundation jcr:primaryType="nt:unstructured">
            <components jcr:primaryType="nt:unstructured">
                <responsivegrid jcr:primaryType="nt:unstructured"/>
            </components>
        </foundation>
    </wcm>
</jcr:root>
