<?xml version="1.0" encoding="UTF-8"?>
<jcr:root xmlns:jcr="http://www.jcp.org/jcr/1.0" xmlns:nt="http://www.jcp.org/jcr/nt/1.0" xmlns:cq="http://www.day.com/jcr/cq/1.0" xmlns:sling="http://sling.apache.org/jcr/sling/1.0"
    jcr:primaryType="cq:Page">
    <jcr:content
        cq:lastModified="{Date}2024-10-23T09:28:00.174+02:00"
        cq:lastModifiedBy="admin"
        cq:policy="fondazione/components/page/policy"
        jcr:primaryType="nt:unstructured"
        sling:resourceType="wcm/core/components/policies/mappings">
        <root
            cq:policy="fondazione/components/container/policy_1574694950110"
            jcr:primaryType="nt:unstructured"
            sling:resourceType="wcm/core/components/policies/mapping">
            <experiencefragment-header
                cq:policy="fondazione/components/experiencefragment/policy_header"
                jcr:primaryType="nt:unstructured"
                sling:resourceType="wcm/core/components/policies/mapping"/>
            <experiencefragment-footer
                cq:policy="fondazione/components/experiencefragment/policy_footer"
                jcr:primaryType="nt:unstructured"
                sling:resourceType="wcm/core/components/policies/mapping"/>
            <container
                cq:policy="fondazione/components/container/policy_649128221558427"
                jcr:primaryType="nt:unstructured"
                sling:resourceType="wcm/core/components/policies/mapping">
                <container
                    cq:policy="fondazione/components/container/policy_1574695586800"
                    jcr:primaryType="nt:unstructured"
                    sling:resourceType="wcm/core/components/policies/mapping">
                    <fondazione jcr:primaryType="nt:unstructured">
                        <components jcr:primaryType="nt:unstructured">
                            <form jcr:primaryType="nt:unstructured">
                                <container
                                    cq:policy="fondazione/components/form/container/form-container"
                                    jcr:primaryType="nt:unstructured"
                                    sling:resourceType="wcm/core/components/policies/mapping"/>
                            </form>
                            <title
                                cq:policy="fondazione/components/title/policy_641528232375303"
                                jcr:primaryType="nt:unstructured"
                                sling:resourceType="wcm/core/components/policies/mapping"/>
                            <text
                                cq:policy="fondazione/components/text/policy_641562756958017"
                                jcr:primaryType="nt:unstructured"
                                sling:resourceType="wcm/core/components/policies/mapping"/>
                            <teaser
                                cq:policy="fondazione/components/teaser/policy_1575031387650"
                                jcr:primaryType="nt:unstructured"
                                sling:resourceType="wcm/core/components/policies/mapping"/>
                            <image
                                cq:policy="fondazione/components/image/policy_651483963895698"
                                jcr:primaryType="nt:unstructured"
                                sling:resourceType="wcm/core/components/policies/mapping"/>
                            <download
                                cq:policy="fondazione/components/download/policy_1575032193319"
                                jcr:primaryType="nt:unstructured"
                                sling:resourceType="wcm/core/components/policies/mapping"/>
                            <banner-app jcr:primaryType="nt:unstructured">
                                <banner-app-container
                                    cq:policy="fondazione/components/banner-app/banner-app-container/policy_69283547620834"
                                    jcr:primaryType="nt:unstructured"
                                    sling:resourceType="wcm/core/components/policies/mapping"/>
                            </banner-app>
                            <banner-mobile-app jcr:primaryType="nt:unstructured">
                                <banner-mobile-app-container
                                    cq:policy="fondazione/components/banner-mobile-app/banner-mobile-app-container/policy_1726061095737"
                                    jcr:primaryType="nt:unstructured"
                                    sling:resourceType="wcm/core/components/policies/mapping"/>
                            </banner-mobile-app>
                            <horizontal-teaser
                                cq:policy="fondazione/components/horizontal-teaser/policy_1726149355415"
                                jcr:primaryType="nt:unstructured"
                                sling:resourceType="wcm/core/components/policies/mapping"/>
                            <card-grid jcr:primaryType="nt:unstructured">
                                <card-grid-container
                                    cq:policy="fondazione/components/card-grid/card-grid-container/policy_1726213078559"
                                    jcr:primaryType="nt:unstructured"
                                    sling:resourceType="wcm/core/components/policies/mapping"/>
                                <card-grid-item
                                    cq:policy="fondazione/components/card-grid/card-grid-item/policy_1726213170851"
                                    jcr:primaryType="nt:unstructured"
                                    sling:resourceType="wcm/core/components/policies/mapping"/>
                            </card-grid>
                            <container
                                cq:policy="fondazione/components/container/policy_34977012579416"
                                jcr:primaryType="nt:unstructured"
                                sling:resourceType="wcm/core/components/policies/mapping"/>
                        </components>
                    </fondazione>
                </container>
                <title
                    cq:policy="fondazione/components/title/policy_641475696923109"
                    jcr:primaryType="nt:unstructured"
                    sling:resourceType="wcm/core/components/policies/mapping"/>
            </container>
        </root>
    </jcr:content>
</jcr:root>
