<?xml version="1.0" encoding="UTF-8"?>
<jcr:root xmlns:jcr="http://www.jcp.org/jcr/1.0" xmlns:nt="http://www.jcp.org/jcr/nt/1.0" xmlns:mix="http://www.jcp.org/jcr/mix/1.0" xmlns:cq="http://www.day.com/jcr/cq/1.0" xmlns:sling="http://sling.apache.org/jcr/sling/1.0"
    jcr:primaryType="cq:Page">
    <jcr:content
        cq:isDelivered="{Boolean}true"
        cq:lastModified="{Date}2023-11-23T14:43:11.419Z"
        cq:lastModifiedBy="d.mariotti@adiacent.com"
        cq:lastReplicated="{Date}2023-10-16T07:58:12.850Z"
        cq:lastReplicated_publish="{Date}2023-10-16T07:58:12.850Z"
        cq:lastReplicatedBy="L.ambrosini@adiacent.com"
        cq:lastReplicatedBy_publish="L.ambrosini@adiacent.com"
        cq:lastReplicationAction="Activate"
        cq:lastReplicationAction_publish="Activate"
        cq:template="/conf/menarini-stemline-uk/settings/wcm/templates/menarini---details-page"
        jcr:isCheckedOut="{Boolean}true"
        jcr:mixinTypes="[cq:ReplicationStatus2,mix:versionable]"
        jcr:primaryType="cq:PageContent"
        jcr:title="Efpia Transparency code"
        jcr:uuid="71983c24-3097-47f4-878d-353f77ce8ed6"
        sling:resourceType="menarinimaster/components/page">
        <root
            jcr:primaryType="nt:unstructured"
            sling:resourceType="menarinimaster/components/container"
            layout="responsiveGrid">
            <container
                jcr:primaryType="nt:unstructured"
                sling:resourceType="menarinimaster/components/container"
                layout="responsiveGrid">
                <internalheader
                    jcr:primaryType="nt:unstructured"
                    sling:resourceType="menarinimaster/components/internalheader"/>
                <section
                    jcr:lastModified="{Date}2023-05-23T15:09:11.542Z"
                    jcr:lastModifiedBy="a.messori@adiacent.com"
                    jcr:primaryType="nt:unstructured"
                    sling:resourceType="menarinimaster/components/section">
                    <wrapper
                        jcr:lastModified="{Date}2023-05-23T15:09:15.286Z"
                        jcr:lastModifiedBy="a.messori@adiacent.com"
                        jcr:primaryType="nt:unstructured"
                        sling:resourceType="menarinimaster/components/wrapper">
                        <breadcrumb
                            jcr:primaryType="nt:unstructured"
                            sling:resourceType="menarinimaster/components/breadcrumb"/>
                    </wrapper>
                </section>
                <container
                    jcr:primaryType="nt:unstructured"
                    sling:resourceType="menarinimaster/components/container"
                    layout="responsiveGrid">
                    <internalmenu
                        jcr:primaryType="nt:unstructured"
                        sling:resourceType="menarinimaster/components/internalmenu"
                        navigationRoot="/content/menarini-stemline-uk/en/transparency"
                        structureStart="{Long}0">
                        <cq:responsive jcr:primaryType="nt:unstructured">
                            <default
                                jcr:primaryType="nt:unstructured"
                                offset="0"
                                width="3"/>
                            <tablet
                                jcr:primaryType="nt:unstructured"
                                offset="0"
                                width="4"/>
                            <phone
                                jcr:primaryType="nt:unstructured"
                                offset="0"
                                width="12"/>
                        </cq:responsive>
                    </internalmenu>
                    <container
                        cq:styleIds="[1684742346871]"
                        jcr:primaryType="nt:unstructured"
                        sling:resourceType="menarinimaster/components/container"
                        layout="responsiveGrid">
                        <title
                            cq:styleIds="[1653552493699]"
                            jcr:lastModified="{Date}2022-07-26T17:40:44.634+02:00"
                            jcr:lastModifiedBy="admin"
                            jcr:primaryType="nt:unstructured"
                            sling:resourceType="menarinimaster/components/title"
                            linkTarget="_self"
                            type="h2">
                            <cq:responsive jcr:primaryType="nt:unstructured">
                                <default
                                    jcr:primaryType="nt:unstructured"
                                    offset="0"
                                    width="5"/>
                            </cq:responsive>
                        </title>
                        <cq:responsive jcr:primaryType="nt:unstructured">
                            <default
                                jcr:primaryType="nt:unstructured"
                                offset="0"
                                width="8"/>
                            <tablet
                                jcr:primaryType="nt:unstructured"
                                offset="0"
                                width="8"/>
                            <phone
                                jcr:primaryType="nt:unstructured"
                                offset="0"
                                width="12"/>
                        </cq:responsive>
                        <container_copy
                            jcr:created="{Date}2023-11-23T14:16:22.276Z"
                            jcr:createdBy="d.mariotti@adiacent.com"
                            jcr:lastModified="{Date}2023-11-23T14:16:41.965Z"
                            jcr:lastModifiedBy="d.mariotti@adiacent.com"
                            jcr:primaryType="nt:unstructured"
                            sling:resourceType="menarinimaster/components/form/container"
                            action="/content/usergenerated/menarini-ch/en/transparency/efpia-transparency-code/cq-gen1700748982284/"
                            actionType="core/wcm/components/form/actions/rpc"
                            externalServiceEndPointUrl="#"
                            id="cmp-efpia"
                            mailAdminText="Placeholder for Admin text"
                            mailClientText="Placeholder for client text">
                            <efpia
                                jcr:created="{Date}2023-11-23T14:38:24.454Z"
                                jcr:createdBy="d.mariotti@adiacent.com"
                                jcr:lastModified="{Date}2023-11-23T14:43:11.377Z"
                                jcr:lastModifiedBy="d.mariotti@adiacent.com"
                                jcr:primaryType="nt:unstructured"
                                sling:resourceType="menarinimaster/components/efpia"
                                folderPath="/content/dam/efpia/menarini-stemline-uk"/>
                            <recaptcha
                                jcr:created="{Date}2023-11-23T14:20:35.920Z"
                                jcr:createdBy="d.mariotti@adiacent.com"
                                jcr:lastModified="{Date}2023-11-23T14:23:08.936Z"
                                jcr:lastModifiedBy="d.mariotti@adiacent.com"
                                jcr:primaryType="nt:unstructured"
                                sling:resourceType="menarinimaster/components/form/recaptcha"
                                publicKey="6LdAvLYoAAAAAJP8cOuLxCMgW-kj3vtuc-GBNYcz"
                                secretKey="6LdAvLYoAAAAAO9ZqRmeH5eCX2THL6CWJA8DwNi0"/>
                            <button
                                jcr:created="{Date}2023-11-23T14:17:49.900Z"
                                jcr:createdBy="d.mariotti@adiacent.com"
                                jcr:lastModified="{Date}2023-11-23T14:18:17.066Z"
                                jcr:lastModifiedBy="d.mariotti@adiacent.com"
                                jcr:primaryType="nt:unstructured"
                                sling:resourceType="menarinimaster/components/form/button"
                                id="efpia-button"
                                type="submit"/>
                            <text
                                jcr:created="{Date}2023-11-23T14:18:48.866Z"
                                jcr:createdBy="d.mariotti@adiacent.com"
                                jcr:lastModified="{Date}2023-11-23T14:42:47.243Z"
                                jcr:lastModifiedBy="d.mariotti@adiacent.com"
                                jcr:primaryType="nt:unstructured"
                                sling:resourceType="menarinimaster/components/text"
                                id="successMessage"
                                text="&lt;h5>Lorem Ipsum Lorem Ipsum Lorem Ipsum&lt;/h5>&#xd;&#xa;"
                                textIsRich="true"/>
                            <button_251674884
                                cq:styleIds="[1653579684271,1653579730618]"
                                jcr:created="{Date}2023-11-23T14:19:45.889Z"
                                jcr:createdBy="d.mariotti@adiacent.com"
                                jcr:lastModified="{Date}2023-11-23T14:31:22.888Z"
                                jcr:lastModifiedBy="d.mariotti@adiacent.com"
                                jcr:primaryType="nt:unstructured"
                                jcr:title="VIew ReportEFpia"
                                sling:resourceType="menarinimaster/components/button"
                                id="efpia-button-report"
                                linkTarget="_self"/>
                        </container_copy>
                    </container>
                </container>
            </container>
        </root>
    </jcr:content>
</jcr:root>
